{"adult":false,"backdrop_path":"/gcJDIOYpb6n1EFN0qDjek2jjPqC.jpg","belongs_to_collection":null,"budget":2700000,"genres":[{"id":28,"name":"Action"},{"id":878,"name":"Science Fiction"}],"homepage":"","id":10017,"imdb_id":"tt0092240","original_language":"en","original_title":"The Wraith","overview":"Packard Walsh and his motorized gang control and terrorize an Arizona desert town where they force drivers to drag-race so they can 'win' their vehicles. After Walsh beats the decent teenager Jamie Hankins to death after finding him with his girlfriend, a mysterious power creates Jake Kesey, an extremely cool motor-biker who has a car which is invincible. Jake befriends Jamie's girlfriend Keri Johnson, takes Jamie's sweet brother Bill under his wing and manages what Sheriff Loomis couldn't; eliminate Packard's criminal gang the hard way...","popularity":12.265,"poster_path":"/oF2RvGGFgw3bke43cWxQNDCcym7.jpg","production_companies":[{"id":10165,"logo_path":null,"name":"New Century Entertainment Corporation","origin_country":""},{"id":10166,"logo_path":null,"name":"Alliance Entertainment","origin_country":""},{"id":59346,"logo_path":null,"name":"Turbo Productions","origin_country":""}],"production_countries":[{"iso_3166_1":"US","name":"United States of America"},{"iso_3166_1":"CA","name":"Canada"}],"release_date":"1986-11-21","revenue":3500000,"runtime":93,"spoken_languages":[{"iso_639_1":"en","name":"English"}],"status":"Released","tagline":"He's not from around here...","title":"The Wraith","video":false,"vote_average":6.1,"vote_count":197}