{"adult":false,"backdrop_path":null,"belongs_to_collection":null,"budget":0,"genres":[{"id":28,"name":"Action"},{"id":35,"name":"Comedy"},{"id":80,"name":"Crime"},{"id":53,"name":"Thriller"}],"homepage":"","id":10026,"imdb_id":"tt0447999","original_language":"en","original_title":"Hot Tamale","overview":"A road trip to Los Angeles inadvertently leads a young man from Wyoming into a wild maze of psychotic hit-men, racy women, jewel thieves and a salsa band.","popularity":6.602,"poster_path":"/stUoCOH6D8iaN7KVOWUwNaRk62b.jpg","production_companies":[],"production_countries":[{"iso_3166_1":"US","name":"United States of America"}],"release_date":"2007-01-01","revenue":0,"runtime":102,"spoken_languages":[{"iso_639_1":"en","name":"English"}],"status":"Released","tagline":"","title":"Hot Tamale","video":false,"vote_average":6.3,"vote_count":12}